[
  {
    "customerId": 1,
    "balance": 500,
    "cart": [
      {
        "bookId": 2,
        "quantity": 1
      },
      {
        "bookId": 3,
        "quantity": 4
      }
    ],
    "createdAt": "2026-07-01T08:30:00Z"
  },
  {
    "customerId": 2,
    "balance": 500,
    "cart": [],
    "createdAt": "2026-07-05T14:15:00Z"
  },
  {
    "customerId": 3,
    "balance": 140,
    "cart": [
      {
        "bookId": 1,
        "quantity": 2
      },
      {
        "bookId": 4,
        "quantity": 1
      }
    ],
    "createdAt": "2026-06-20T10:00:00Z"
  },
  {
    "customerId": 4,
    "balance": 20,
    "cart": [
      {
        "bookId": 3,
        "quantity": 1
      }
    ],
    "createdAt": "2026-07-08T09:45:00Z"
  }
]